vnpy_duckdb/__init__.py
vnpy_duckdb/duckdb_database.py
vnpy_duckdb/duckdb_sql.py
vnpy_duckdb-1.0.0.dist-info/LICENSE
vnpy_duckdb-1.0.0.dist-info/METADATA
vnpy_duckdb-1.0.0.dist-info/WHEEL
vnpy_duckdb-1.0.0.dist-info/top_level.txt
vnpy_duckdb-1.0.0.dist-info/RECORD
